gnsq/__init__.py
gnsq/backofftimer.py
gnsq/consumer.py
gnsq/decorators.py
gnsq/errors.py
gnsq/httpclient.py
gnsq/lookupd.py
gnsq/message.py
gnsq/nsqd.py
gnsq/producer.py
gnsq/protocol.py
gnsq/reader.py
gnsq/states.py
gnsq/util.py
gnsq/version.py
gnsq/contrib/__init__.py
gnsq/contrib/batch.py
gnsq/contrib/giveup.py
gnsq/contrib/queue.py
gnsq/contrib/sentry.py
gnsq/stream/__init__.py
gnsq/stream/compression.py
gnsq/stream/defalte.py
gnsq/stream/snappy.py
gnsq/stream/stream.py
gnsq-1.0.2.dist-info/AUTHORS.rst
gnsq-1.0.2.dist-info/LICENSE
gnsq-1.0.2.dist-info/METADATA
gnsq-1.0.2.dist-info/WHEEL
gnsq-1.0.2.dist-info/top_level.txt
gnsq-1.0.2.dist-info/RECORD
