Metadata-Version: 2.1
Name: gnsq
Version: 1.0.2
Summary: A gevent based python client for NSQ.
Home-page: https://github.com/wtolson/gnsq
Author: Trevor Olson
Author-email: trevor@heytrevor.com
License: BSD
Keywords: gnsq
Platform: UNKNOWN
Classifier: Development Status :: 5 - Production/Stable
Classifier: Intended Audience :: Developers
Classifier: License :: OSI Approved :: BSD License
Classifier: Natural Language :: English
Classifier: Programming Language :: Python :: 2
Classifier: Programming Language :: Python :: 2.7
Classifier: Programming Language :: Python :: 3
Classifier: Programming Language :: Python :: 3.4
Classifier: Programming Language :: Python :: 3.5
Classifier: Programming Language :: Python :: 3.6
Classifier: Programming Language :: Python :: 3.7
Requires-Dist: blinker
Requires-Dist: gevent
Requires-Dist: six
Requires-Dist: urllib3
Provides-Extra: snappy
Requires-Dist: python-snappy ; extra == 'snappy'
